dataMovies/__init__.py
dataMovies/dataMoviesFeatures.py
dataMovies/errors/error.py
dataMovies/errors/imdbServiceErrors.py
dataMovies/serializers/imdbSerializers.py
dataMovies/serializers/utils/dictionaryTransform.py
dataMovies/services/imdbService/__init__.py
dataMovies/services/imdbService/imdbApiCall.py
dataMovies/services/imdbService/imdbEndPoint.py
dataMovies/services/imdbService/imdbRequests.py
dataMovies/services/imdbService/imdbResponse.py
dataMovies/services/imdbService/imdbService.py
dataMovies/services/imdbService/utils/imdbUtils.py
datamovies-0.0.15.dist-info/METADATA
datamovies-0.0.15.dist-info/WHEEL
datamovies-0.0.15.dist-info/licenses/LICENSE
datamovies-0.0.15.dist-info/RECORD
