Metadata-Version: 2.1
Name: dataMovies
Version: 0.0.15
Summary: Movies datasets package based on Imdb API.
Project-URL: Homepage, https://github.com/rizerkrof/libray-dataMovies
Project-URL: Bug Tracker, https://github.com/rizerkrof/libray-dataMovies/issues
Author-email: Edouard Lacourt <edouardlacourt8@gmail.com>
License-File: LICENSE
Classifier: License :: OSI Approved :: MIT License
Classifier: Operating System :: OS Independent
Classifier: Programming Language :: Python :: 3
Requires-Python: >=3.8
Requires-Dist: pandas~=1.5.1
Requires-Dist: python-dotenv~=0.21.0
Requires-Dist: requests~=2.28.0
